webullpaysdkcore/__init__.py
webullpaysdkcore/client.py
webullpaysdkcore/compat.py
webullpaysdkcore/headers.py
webullpaysdkcore/request.py
webullpaysdkcore/auth/__init__.py
webullpaysdkcore/auth/credentials.py
webullpaysdkcore/auth/algorithm/__init__.py
webullpaysdkcore/auth/algorithm/sha_hmac1.py
webullpaysdkcore/auth/algorithm/sha_hmac256.py
webullpaysdkcore/auth/composer/__init__.py
webullpaysdkcore/auth/composer/default_signature_composer.py
webullpaysdkcore/auth/signers/__init__.py
webullpaysdkcore/auth/signers/app_key_signer.py
webullpaysdkcore/auth/signers/signer.py
webullpaysdkcore/auth/signers/signer_factory.py
webullpaysdkcore/cache/__init__.py
webullpaysdkcore/common/__init__.py
webullpaysdkcore/common/api_type.py
webullpaysdkcore/common/easy_enum.py
webullpaysdkcore/common/region.py
webullpaysdkcore/data/endpoints.json
webullpaysdkcore/data/retry_config.json
webullpaysdkcore/endpoint/__init__.py
webullpaysdkcore/endpoint/chained_endpoint_resolver.py
webullpaysdkcore/endpoint/default_endpoint_resolver.py
webullpaysdkcore/endpoint/local_config_regional_endpoint_resolver.py
webullpaysdkcore/endpoint/resolver_endpoint_request.py
webullpaysdkcore/endpoint/user_customized_endpoint_resolver.py
webullpaysdkcore/exception/__init__.py
webullpaysdkcore/exception/error_code.py
webullpaysdkcore/exception/error_msg.py
webullpaysdkcore/exception/exceptions.py
webullpaysdkcore/http/__init__.py
webullpaysdkcore/http/method_type.py
webullpaysdkcore/http/protocol_type.py
webullpaysdkcore/http/request.py
webullpaysdkcore/http/response.py
webullpaysdkcore/retry/__init__.py
webullpaysdkcore/retry/backoff_strategy.py
webullpaysdkcore/retry/retry_condition.py
webullpaysdkcore/retry/retry_policy.py
webullpaysdkcore/retry/retry_policy_context.py
webullpaysdkcore/utils/__init__.py
webullpaysdkcore/utils/common.py
webullpaysdkcore/utils/data.py
webullpaysdkcore/utils/validation.py
webullpaysdkcore/vendored/__init__.py
webullpaysdkcore/vendored/six.py
webullpay_python_sdk_core-0.1.0.dist-info/METADATA
webullpay_python_sdk_core-0.1.0.dist-info/WHEEL
webullpay_python_sdk_core-0.1.0.dist-info/top_level.txt
webullpay_python_sdk_core-0.1.0.dist-info/RECORD
