Metadata-Version: 2.4
Name: webullpay-python-sdk-core
Version: 0.1.0
Summary: The core module of Webullpay Python SDK.
Home-page: 
Author: Webullpay
Author-email: 
License: Apache License 2.0
Platform: any
Requires-Dist: jmespath<1.0.0,>=0.9.3
Requires-Dist: cryptography>=2.6.0
Requires-Dist: cachetools==5.2.0
Requires-Dist: urllib3>=2.0.2
Dynamic: author
Dynamic: description-content-type
Dynamic: license
Dynamic: platform
Dynamic: requires-dist
Dynamic: summary
